{
  "update_time": "2026-04-08 06:34:41",
  "update_date": "2026-04-08",
  "category_id": -1,
  "total_count": 6,
  "books": [
    {
      "hot_rank": 203,
      "book_id": "7608243823344372798",
      "book_name": "每夜都被病娇男主强取豪夺！",
      "author": "榴莲奶酪",
      "tags": [
        "豪门总裁",
        "现代言情",
        "总裁",
        "甜宠",
        "病娇",
        "穿书"
      ],
      "abstract": "刚开分，后面会涨\n【女主身娇体软易推倒x男主会哄不会停的阴暗病娇】\n\n许怜柔穿书了，穿成书里胸大腰软的娇美恶毒女配。\n却不知道怎么回事被男主盯上了。\n在病娇男主的手段下，她不得不选择跟他在一起。\n只是，她没有想到男主不仅是个大病娇，还丝毫没有节制，日日夜夜缠着她。\n身娇敏感的许怜柔压根受不住…\n（拉扯甜文，放心看）",
      "status": "Ongoing",
      "thumb_url": "https://p9-novel-sign.byteimg.com/novel-pic/b93416189bfe64c9792bf73049f44a52~tplv-resize:225:300.image?lk3s=191c1ecc&x-expires=1775687647&x-signature=kW7WoDvv5JI46vX0tZhizHoaAro%3D",
      "last_chapter_time": "1775575710",
      "rank_change": "new"
    },
    {
      "hot_rank": 214,
      "book_id": "7614438704576220184",
      "book_name": "卖爹去入赘，我被三个继兄轮流宠",
      "author": "蹦跶兔",
      "tags": [
        "年代",
        "现代言情",
        "乡村",
        "宠妻",
        "相互救赎",
        "家长里短"
      ],
      "abstract": "【娇气貌美小太阳女主+宠妻狂魔糙汉男主】+双向救赎+家长里短\n\n沈明珠，重生后第一件事，就是送爹去入赘！\n\n前世被冯家父子折磨得人不人鬼不鬼，临死前才知道，亲妈带走的“好日子”是地狱，留在乡下的姐姐恨她入骨。\n\n这一世，看着亲妈又要带人走，姐姐跪着抢着要跟去——\n\n沈明珠笑了。\n\n她转身就上了后山，找到那个惦记她爸多年的女猎户：\n\n“三妞姨，你想不想娶我爸？”\n\n钱三妞：？？？\n\n三个继兄：？？？\n\n亲爹沈恒远：？？？\n\n后来——\n\n她爸入赘猎户家，天天有肉吃，被后娘宠得脸红心跳。\n\n三个继兄，一个憨厚老实，一个嘴碎心软，还有一个人狠话不多，总是默默地为她做了许多事的。\n\n而跟着亲妈走的姐姐，正欢天喜地奔向那个“吃人不吐骨头”的冯家。\n\n沈明珠：谢了，这福气给你，我要领着全家奔小康。\n\n手撕白莲，绝不内耗，带着后娘和三个继兄，六十年代也要活得滋滋润润！",
      "status": "Ongoing",
      "thumb_url": "https://p3-novel-sign.byteimg.com/novel-pic/p2o1a7fdd7ce522eabf1f8c3758247dc7be~tplv-resize:225:300.image?lk3s=191c1ecc&x-expires=1775687652&x-signature=NSTDsKUfajJTbHDRy00gPdWqwMY%3D",
      "last_chapter_time": "1775577684",
      "rank_change": "new"
    },
    {
      "hot_rank": 234,
      "book_id": "7487969155233090584",
      "book_name": "开局被卖，我在王府开启逆袭之路",
      "author": "苍蛟",
      "tags": [
        "宫斗宅斗",
        "古代言情",
        "腹黑",
        "扮猪吃虎",
        "甜宠",
        "搞笑轻松"
      ],
      "abstract": "《腹黑世子vs清纯姑娘+天生神力+轻松+不虐+》阿奴出生在一个贫穷到连饭都吃不饱的家庭，偏偏弟弟妹妹同时生病，家里又穷的叮当响，没办法，只能把自己卖给了广陵王府当奴婢，听说大户人家的主子可难伺候了，一旦被主子们相中抬成姨娘，那早晚得被主母给弄死了，因此她不想当姨娘，便给自己剪了一个极为丑陋的西瓜头，挡住了好看的眉眼，本以为这样不会有人注意到她了，没想到一进王府，就被大魔头世子要了过去，为了不出错，她尽量少说话多干活，可她越不想出错，闹的笑话就越多，也成功的引起了世子的注意力，发现了她天生神力的潜能。\n娄玄毅：想赚钱吗？\n阿奴：想！\n娄玄毅：只要你按我要求做，这些钱都是你的。\n阿奴：世子，您说话可得算数！",
      "status": "Ongoing",
      "thumb_url": "https://p9-novel-sign.byteimg.com/novel-pic/p2o8a49827c00ec4e551b22ef01bef07d27~tplv-resize:225:300.image?lk3s=191c1ecc&x-expires=1775687654&x-signature=OB%2FGJ%2BatUEp0CLFqmSyfUoPDUbM%3D",
      "last_chapter_time": "1775577738",
      "rank_change": "new"
    },
    {
      "hot_rank": 256,
      "book_id": "7495281423935343641",
      "book_name": "晏先生，太太给您留了离婚协议书",
      "author": "夜雨绵",
      "tags": [
        "豪门总裁",
        "现代言情",
        "豪门世家",
        "大佬",
        "追妻",
        "年龄差"
      ],
      "abstract": "【上位者低头+双洁】\n　　身份不明的孤女向云莞，嫁给了顶级豪门晏家长孙——晏承序。\n　　\n　　她以为会迎来幸福，没想到迎来的却是冷待。\n　　\n　　结婚四年，丈夫晏承序一直与她分房睡，连她的手指头都不曾碰过。\n　　\n　　他的身影出现在各大新闻头条，身边陪伴的永远是江远集团千金，江书瑶。\n　　\n　　心灰意冷后，向云莞留下离婚协议书，搬着东西离开婚房，决定成全他们的幸福。\n　　\n　　那个冷落了她四年的男人，却如同疯了般，将她抵在沙发上，嗓音沙哑失控：“还没睡过呢，就想离婚？先把这四年的补偿回来再说！”\n　　\n　　——————\n　　\n　　太太向云莞是他放在心尖上，不敢触碰的月光。\n　　\n　　可某一天，月光忽然离他而去。\n　　\n　　他用尽一切手段将月光寻回，牢牢困在身边，只愿她独照自己！\n【男主眼里心里，自始至终只有女主一人，没有出轨！】",
      "status": "Ongoing",
      "thumb_url": "https://p9-novel-sign.byteimg.com/novel-pic/p2od2ad0e2df1df5b93e708ce93caac9176~tplv-resize:225:300.image?lk3s=191c1ecc&x-expires=1775687658&x-signature=2lf1bQKFdYw%2FWCx5lpNtqPJjZws%3D",
      "last_chapter_time": "1775580518",
      "rank_change": "new"
    },
    {
      "hot_rank": 278,
      "book_id": "7614502274148076568",
      "book_name": "开局：召唤魅魔，竟是房东太太！",
      "author": "小小怪将军007",
      "tags": [
        "动漫衍生",
        "开局",
        "都市",
        "多女主",
        "系统",
        "穿越"
      ],
      "abstract": "【日恐+多女主+偏日常+诡异骑士】\n宁夜穿越到一个鬼怪横行的危险世界，刚醒过来就有女鬼想找他碰一碰，在这危机时刻，他的金手指出现了。\n只要击杀或击败诡异、妖怪等等，就能随机掉落三个光球，从中可以开出功法、道具、甚至特殊体质！\n厉害是厉害，但现在没用啊，于是他看到了手中前身留下的一本破旧书籍。\n《召唤阵：教你如何召唤一只听话的魅魔》\n宁夜：？？？\n这个世界的自己都这么帅气逼人了，还研究这个？\n但现在是紧要关头，他顾不上什么了，本着活马当死马医的原则，随手摆下召唤阵。\n但压根就没指望能成，毕竟这玩意儿听着就像骗人的。\n然而，随着启动，阵法真亮了！！！\n随着紫色光芒散去，一个熟悉的身影出现在阵法中央，有着爱心尾巴、小翅膀、和魅魔角！\n宁夜见状，瞳孔猛缩：\n“兄弟们，我先冲了！！！”",
      "status": "Ongoing",
      "thumb_url": "https://p6-novel-sign.byteimg.com/novel-pic/2ddd968f25bfab3af25e63b4e8666d26~tplv-resize:225:300.image?lk3s=191c1ecc&x-expires=1775687663&x-signature=JGZJgop08q1g02xszG16idxO%2FBU%3D",
      "last_chapter_time": "1775577690",
      "rank_change": "new"
    },
    {
      "hot_rank": 326,
      "book_id": "7567657861308746814",
      "book_name": "睁眼六零军区，弄错对象被亲哭了",
      "author": "咿伊",
      "tags": [
        "年代",
        "现代言情",
        "穿书",
        "大佬",
        "家长里短"
      ],
      "abstract": "睁眼六零，许穗在男人床上醒来，被狠狠折腾了一整夜，亲哭晕死过去，一夜揣上双胎\n她这才发现自己穿书了。\n穿成肤白貌美，身姿窈窕的漂亮恶毒小青梅，前往军区找男主结婚，却意外弄错对象爬错床，被迫嫁给了落魄的假少爷。\n婚后顾云舟出任务断了腿，原主转头卷钱打胎跑路，最后钱丢了，身子骨坏了，大动荡被人举报作风问题惨死。\n顾云舟不仅腿好了，还重返部队步步高升，成为有权有势军区大佬，成了军区炙手可热的存在，惹得多少人想攀上他这根高枝。\n许穗看着眼前斯文俊美的军官男人，摸着肚子里的崽：长得帅，有本事，能力强，也不是不行。\n这么好的潜力股，可不能便宜了别人。\n*\n顾云舟不喜欢许穗。\n然而，婚后自家媳妇漂亮又勾人。\n一夜就怀上他的种，还是龙凤胎。\n怀着双胎轻松考上粮站铁饭碗，转头又成为六十年代顶尖大学高级人才，发明这个，发明那个，办厂赚外汇，让大伙儿富起来，成为领导座上宾。\n两个娃随媳妇，是有名的天才儿童。\n老实婆家：瞧见没，软弱了大半辈子的老秦家终于迎来了主心骨。\n成了首长夫人的心机寡妇娘：瞧，我闺女上报纸了。\n某首长：这是咱闺女，咱闺女就是厉害。\n被许穗带富的军嫂们：谁敢说许厂长坏话，就撕谁的嘴！",
      "status": "Ongoing",
      "thumb_url": "https://p6-novel-sign.byteimg.com/novel-pic/p2o3a797cd14f17880a6b9c07b765e314f4~tplv-resize:225:300.image?lk3s=191c1ecc&x-expires=1775687679&x-signature=civtLR8pLJUTAvZDVqvnolN%2BzOE%3D",
      "last_chapter_time": "1775577397",
      "rank_change": "new"
    }
  ]
}