{
  "update_time": "2026-05-16 17:16:17",
  "update_date": "2026-05-16",
  "category_id": 1169,
  "total_count": 36,
  "books": [
    {
      "hot_rank": 17,
      "book_id": "7623743402533719064",
      "book_name": "凶案现场，我这个美少女能看见鬼",
      "author": "原来是夏天",
      "tags": [
        "女频悬疑",
        "悬疑",
        "推理",
        "破案",
        "悬疑恋爱"
      ],
      "abstract": "沈窈窈是个社恐大学生，却阴差阳错进了全城最神秘的“特调局”。\n局里全是各界顶级大佬：冷面杀神队长、黑客界顶流、人形测谎仪法医。\n没人看好这个软糯糯的沈窈窈，直到……\n碎尸案死者：警官，凶手是我前男友，他杀我是因为我发现他脚踩八只船！\n密室消失案死者：别查了，我死在天花板里，凶手这会儿正蹲在你们脚底下挖洞呢。\n沈窈窈一边吃瓜一边指路：“那啥，死者说凶手在你们后头。”\n全员：“！！！”\n从此，沈窈窈成了局里的“镇局之宝”，各大案现场只见一群大佬在前面冲锋陷阵，沈窈窈蹲在后头跟死者分零食。",
      "status": "Ongoing",
      "thumb_url": "https://p6-novel-sign.byteimg.com/novel-pic/p2o8ee2ee2fd38d95216fa457beb086e1c1~tplv-resize:225:300.image?lk3s=191c1ecc&x-expires=1779005780&x-signature=gMwbAfZH2n%2F1hJ8GJVt7w1znlKY%3D",
      "last_chapter_time": "1778913015",
      "first_chapter_time": 1775041179,
      "rank_change": "new"
    },
    {
      "hot_rank": 21,
      "book_id": "7620318256322071576",
      "book_name": "当个社畜，怎么成凶案嫌疑人了？",
      "author": "一斤小胖墩",
      "tags": [
        "女频悬疑",
        "悬疑",
        "推理",
        "天才",
        "破案",
        "悬疑恋爱"
      ],
      "abstract": "刚开分，后面会涨！请放心食用\n逻辑天才实习生×高冷禁欲护短刑警队长1v1，双洁双强，架空，含私设。\n姜绵只是下楼拿个雷霆外卖，就撞上小区垃圾桶发现人民碎片。\n她挤进人群吃瓜，下一秒直接被目击证人指认成凶手。\n姜绵：满脸???，别这么离谱行不？她只是吃个瓜！怎么成凶手了？\n刑警队队长宋延，高冷禁欲，不近人情，一开口就把她按在嫌疑人位置上磋磨。\n“说一下作案过程。”\n语气恶劣，还把她当小猫似的逗了一通。姜绵气炸，幸好天降神探系统，当场洗清嫌疑。\n但她万万没料到自己倒霉到竟被学校分配到临江市刑警支队实习。\n上司，还是宋延!!\n直到某天，姜绵发现，这位高冷禁欲的队长，一跟她对视就耳尖发红。\n她笑眯眯凑近：“宋队，你中暑了?”\n宋延绷着脸：“没有。”\n姜绵挑眉：“那就是……对我心动了。” \n再后来她更惊了。\n这人在床上既不高冷，也不禁欲。\n分明是个装正经的大涩迷！！！\n清水河里，钓友钓起一具高度腐败……\n空置出租屋，夜半墙缝渗出暗红水渍。\n诡异村庄，看似村风纯朴，实则暗藏恐怖陋习。\n腐生菌丛、假面新郎、骨影灯笼……\n一桩桩离奇凶案，撕开人性最黑暗的褶皱。\n而她和他，在刀尖上追凶，也在心动里沦陷。",
      "status": "Ongoing",
      "thumb_url": "https://p3-novel-sign.byteimg.com/novel-pic/p2ob625a8ae8c9a3f5246ff84b9df8a0a5c~tplv-resize:225:300.image?lk3s=191c1ecc&x-expires=1779005784&x-signature=cWP6qF1EBJzKJ2srx1bQ%2BautCO4%3D",
      "last_chapter_time": "1778918275",
      "first_chapter_time": 1774694188,
      "rank_change": "new"
    },
    {
      "hot_rank": 24,
      "book_id": "7588095605168163865",
      "book_name": "三嫁阎君",
      "author": "王权月初",
      "tags": [
        "女频悬疑",
        "悬疑",
        "灵异",
        "悬疑恋爱",
        "风水秘术"
      ],
      "abstract": "二十岁这年，我爸给我抢了一桩人人都惧怕的婚事。\n婚期定在七月十五，鬼节，而我要嫁的他……\n也不是人。\n只因我出生就没有心跳，是我爸用秘术吊着我的命，只有和这个神秘老公结婚才能得一线生机。\n成婚当天夜里，漫天飞舞的纸钱中，诡异的纸人携着八抬凤辇从天而降。\n我代替了同村少女成为了他的妻。\n结婚后，父亲诡异失踪，留下一本《世间百鬼录》，从此我携百鬼录踏入了奇幻诡谲的世界。\n千年尸王是我的保镖，万年灵物成为我的法器，渡灵扇在手了却世间万千执念，灵愈之力治愈三界山精鬼怪，我成为世间独一无二的渡灵师。\n而我的那个神秘老公，他说娶我非他所愿，等到约定期限一到，他便给我自由并赐予我长命百岁。\n我欣然接受，离婚而已，可以再嫁。\n可是……\n我都三嫁了，新郎怎么还是他？",
      "status": "Ongoing",
      "thumb_url": "https://p3-novel-sign.byteimg.com/novel-pic/p2o6040e25387ebd21e6ba0876225c547be~tplv-resize:225:300.image?lk3s=191c1ecc&x-expires=1779005788&x-signature=2WG4tHBuDIFyqUcGCie8w%2BjqML8%3D",
      "last_chapter_time": "1778860389",
      "first_chapter_time": 1766742200,
      "rank_change": "new"
    },
    {
      "hot_rank": 25,
      "book_id": "7591911021179046936",
      "book_name": "夏洛克：人在贝克街苟活全靠弹幕",
      "author": "桃桃er酱",
      "tags": [
        "女频悬疑",
        "悬疑",
        "推理",
        "破案",
        "同人",
        "悬疑恋爱"
      ],
      "abstract": "【英美剧+弹幕+搞笑+迪化+正文非CP向+神探夏洛克】\n（前排劝退：BBC剧《神探夏洛克》同人，女主设定是靠弹幕苟活的社畜，没什么大能耐，系统就这么个坏蛋，不喜欢的宝宝别看了，及时止损退出，不用浪费时间写评论告诉我写的不好👌正文已完结！补充：番外和某些章节正文后的小剧场，不嗑的别看别看，接受不了番外cp的现在就可以退出，写文不易，理解万岁）\n———\n穿越到苏格兰场当文员，林恩唯一的愿望就是活到养老金发放的那一天。\n可谁能告诉她，为什么她眼前全是来自三次元的【剧情弹幕】？\n案发现场，由于弹幕剧透，她顺手救下了差点领便当的雷斯垂德，结果却招惹上了那个全伦敦最麻烦的男人——夏洛克·福尔摩斯。\n看着头顶飘过“卷福正在分析你早餐吃了什么”的弹幕，林恩只想逃跑。\n系统警告：【远离主角团=死亡率100%】。\n为了苟命，她被迫成为夏洛克的“人形外挂”。\n夏洛克：“排除所有不可能，剩下的就是真相。林恩，你怎么看？”\n林恩盯着弹幕上的【凶手是那个花匠，凶器在花盆底】，面无表情地棒读：“我觉得花匠很可疑。”\n夏洛克目光灼灼：“果然，只有你的思维能跟上我的节奏。”\n林恩：“……”\n救命，她真的只是在读弹幕啊！",
      "status": "Ongoing",
      "thumb_url": "https://p6-novel-sign.byteimg.com/novel-pic/p2o6d4244d8e416fc979c4f7830f16503a7~tplv-resize:225:300.image?lk3s=191c1ecc&x-expires=1779005789&x-signature=KmYQfkwIHiX%2BxJU%2Bv6ifK8kkP4Q%3D",
      "last_chapter_time": "1778860920",
      "first_chapter_time": 1767795121,
      "rank_change": "new"
    },
    {
      "hot_rank": 26,
      "book_id": "7612308380547288126",
      "book_name": "饲养员又被怪物包围",
      "author": "梅尔乔尔",
      "tags": [
        "悬疑脑洞",
        "悬疑",
        "悬疑恋爱",
        "灵异"
      ],
      "abstract": "【万人迷杰克苏+美恐+怪谈+微克+饲养怪物】\n穆睡，伊卡洛斯研究院的华裔研究员，上一秒还在研究院的培养仓里哄睡怪物，下一秒被怪物哄睡。\n再睁眼，穆睡流落到暴力与怪物横生的米国街头，全身上下只有一张工牌。\n他寻求警员的帮助，警员却在录制死前的留影：\n——“尊敬的穆睡先生，米国从来都没有设立过任何一家名为‘伊卡洛斯’的研究院。”\n——“尊敬的穆睡先生，怪物是听不懂人话的。”\n——“尊敬的穆睡先生，您是否应该解释一下，为什么这些怪物都在对您摇尾巴呢？”\n\n【注意：世界观架空，与现实历史走向无关，书中所出现的时间节点不一定正确。】",
      "status": "Ongoing",
      "thumb_url": "https://p3-novel-sign.byteimg.com/novel-pic/6190d92af3a3fec1e0edc68c8cd90133~tplv-resize:225:300.image?lk3s=191c1ecc&x-expires=1779005790&x-signature=eSGgafO7tpga9pRr6GScM%2BPeWs0%3D",
      "last_chapter_time": "1778860550",
      "first_chapter_time": 1772812359,
      "rank_change": "new"
    },
    {
      "hot_rank": 28,
      "book_id": "7550401537575488537",
      "book_name": "和张起灵分手后，他要炸了青铜门",
      "author": "火淼未济",
      "tags": [
        "女频悬疑",
        "悬疑",
        "盗墓",
        "灵异",
        "同人",
        "悬疑恋爱"
      ],
      "abstract": "【盗墓同人➕原创女主➕狗血拉扯➕微悬疑➕CP张起灵➕追妻】\n相恋两年的男朋友断崖式失联，再次相见，项卿拿着洛阳铲，张起灵扛着黑金刀。\n项卿：前男朋友又又又失忆了怎么办？\n张起灵：……记笔记，媳妇，我的……\n（剧情原创，沿用盗笔人物名。）\n暂定故事：\n《檀抜土司城》苗疆➕蛊仙继承，项卿与张起灵重逢。\n《九眼桥精神卫生中心》藏在都市里的地下墓穴。\n……",
      "status": "Ongoing",
      "thumb_url": "https://p9-novel-sign.byteimg.com/novel-pic/p2o0ea29b7efb3dd63e94d412d3ced5916b~tplv-resize:225:300.image?lk3s=191c1ecc&x-expires=1779005793&x-signature=%2BerHgiCooaP9ZoOpgVEvvhZfAe8%3D",
      "last_chapter_time": "1778917957",
      "first_chapter_time": 1757964988,
      "rank_change": "new"
    },
    {
      "hot_rank": 31,
      "book_id": "7625503968617057304",
      "book_name": "90小片警：惊！又在案发现场",
      "author": "柿你吗",
      "tags": [
        "女频悬疑",
        "悬疑",
        "穿越",
        "推理",
        "破案",
        "悬疑恋爱"
      ],
      "abstract": "救命啊，21世纪社畜竟然穿成了90年代的小片警，她完全不会啊，这怎么搞？等等，90年代？大学生？包分配！重点培养！！！老天奶还亲赐梦回案发现场的金手指，沈梦晴眼睛亮了亮，顿时觉得：嗳，可以了！水库抛尸案、少女失踪案……案案难破，案案破。搞男人有什么意思，当白月光的领导更有意思，来，喊一声领导。韩辰：不是说暗恋我吗？",
      "status": "Ongoing",
      "thumb_url": "https://p3-novel-sign.byteimg.com/novel-pic/p2oc079b28c803cd200fef2fdc499279e2a~tplv-resize:225:300.image?lk3s=191c1ecc&x-expires=1779009340&x-signature=E5FcdB%2BOcCCEoaQxHUe3C3Awj3c%3D",
      "last_chapter_time": "1778922680",
      "first_chapter_time": 1775452151,
      "rank_change": "new"
    },
    {
      "hot_rank": 37,
      "book_id": "7591716077432753177",
      "book_name": "摸骨断大案",
      "author": "吉诚",
      "tags": [
        "女频悬疑",
        "悬疑",
        "穿越",
        "推理",
        "破案",
        "悬疑恋爱"
      ],
      "abstract": "现代法医苏乔，意外身死魂穿成扬州赌鬼养女，这开局就遇绝境，被卖青楼！\n为自救，她盯上了楼中那位气势慑人的锦衣卫指挥使——萧纵。\n千机阁悬案压城，腐尸难辨。\n“大人，我会仵作之术，可助你破案，但你，可否救我出青楼。”\n众目睽睽下，她徒手验骨，复原亡者容颜。\n萧纵冷眼审视这突然撞入局中的女子，\n调查得知，她养父嗜赌卖女，巧合得可笑！\n既然如此，打包带走吧！\n将她带在身边，她成了北镇抚司专属仵作。\n屡破奇案，她聪慧果决，而他杀伐果决，却屡次为她破例，护她周全。\n他曾当众说：“我是萧纵——无限纵容苏乔的纵。”\n她亦在他过往伤痛前驻足，轻声却坚定：“萧大人，让我当你的家人。”\n从此，冰山权臣有了软肋，穿越法医有了归处。\n原书名《摸骨断大案》",
      "status": "Completed",
      "thumb_url": "https://p9-novel-sign.byteimg.com/novel-pic/796cabaaa30c0497e529dad4a95fa682~tplv-resize:225:300.image?lk3s=191c1ecc&x-expires=1779009342&x-signature=7gcUSXdsKdLnIHDhKkY56rlmy38%3D",
      "last_chapter_time": "1775003926",
      "first_chapter_time": 1767584543,
      "rank_change": "new"
    },
    {
      "hot_rank": 40,
      "book_id": "7618966576464661528",
      "book_name": "疯批美人！靠读心术卷成警界传说",
      "author": "石狗二村",
      "tags": [
        "女频悬疑",
        "悬疑",
        "悬疑恋爱",
        "推理",
        "天才",
        "破案"
      ],
      "abstract": "【刑侦+悬疑+强强+疯批美人+爽文+读心神探】\n三年前，天才侧写师江瞳在一次任务中跌落神坛，搭档惨死，她被当成疯子强制“休养”。\n三年后，一桩手法诡异的“艺术品”谋杀案震惊全市，束手无策的警队，不得已请回了这位被封杀的疯批美人。\n重返警局，迎接她的是所有人的猜忌和冰山队长秦漠的绝对敌视。\n同事：“她就是个疯子，会毁了我们！”\n秦漠：“管好你的精神状态，否则就滚出去！”\n江瞳红唇一勾，笑得肆意又危险：“队长，你心跳快了0.5秒，是怕我，还是爱上我？”\n面对最狡猾的罪犯，她是最顶级的猎手。\n蛛丝马迹在她眼中无所遁形，谎言在她耳边自动分解。\n她能看穿人心，也能玩弄人心。她以身为饵，诱罪犯入网；她以疯为刃，刺破一切伪装。\n当一桩桩奇案被她用匪夷所思的方式侦破，整个警局都炸了！\n那个他们眼中的疯子，竟是藏得最深的王牌！\n而冰山队长秦漠看着她浴血而立，眼神里只剩下了沉沦和占有欲。\n秦漠：“江瞳，你是我的深渊，我心甘情愿。”\n江瞳：“不，我是你的女王，为你加冕，也为你断头。”",
      "status": "Ongoing",
      "thumb_url": "https://p3-novel-sign.byteimg.com/novel-pic/p2ob82352f810f15311def7d4897fc7dfcb~tplv-resize:225:300.image?lk3s=191c1ecc&x-expires=1779009343&x-signature=rFBJNAIwluf%2B%2FbMu3wxidPJO4yw%3D",
      "last_chapter_time": "1778886507",
      "first_chapter_time": 1773931676,
      "rank_change": "new"
    },
    {
      "hot_rank": 43,
      "book_id": "7485202789027548184",
      "book_name": "沙海：谁家的继妹这么让人心梗啊",
      "author": "深意y",
      "tags": [
        "女频悬疑",
        "悬疑",
        "穿越",
        "灵异",
        "同人",
        "悬疑恋爱"
      ],
      "abstract": "【搞笑+又怂又毒舌+ooc警告+沙雕+all+成长型女主+非圣母+团宠小可爱+巴掌王者扇一切】\n因为前一天写小作文欺负黎簇，结果第二天就开始各种倒霉。\n掉进下水道前，她发誓再也不欺负黎簇了。\n结果睁开眼睛，她就成为了黎簇的继妹。\n报应来的太快，让她有点反应不过来。\n为了打断水逆，她将黎簇视为生命中第n重要的事情。\n和吴邪抗争到底！\n逼黎簇回去复读。\n结果黎簇没什么出息…\n她混成了张汪两家的掌公主。\n在她即将开枪前解决叛徒前，黎簇将她牢牢护在怀里：有我在，你永远不需要脏了自己的手。\n汪灿在毒瘴弥漫的雨林里，扯下防毒面具：如果我活着不能让你信，那我就死给你看。\n吴邪满脸狼狈却又认真的看着她：喜欢你怎么了？犯法吗？\n黑瞎子背着她飞跃断层，语气戏谑却又可靠：掉下去也行啊，黄泉路上有个漂亮的小姑娘陪着，我走得也不寂寞啊\n张起灵作为靠谱“老爹”安全感爆棚，直到父爱变质，许思仪长吁短叹，她肯定是有点什么说法，说不定是招点什么。\n许思仪：扇不过来，根本扇不过来…",
      "status": "Ongoing",
      "thumb_url": "https://p6-novel-sign.byteimg.com/novel-pic/p2o953479e5f93bc588ea5a2479bb1bfcb7~tplv-resize:225:300.image?lk3s=191c1ecc&x-expires=1779009344&x-signature=TFWzRI7Oz3YcgI6p8g7ASDlyZTw%3D",
      "last_chapter_time": "1778860885",
      "first_chapter_time": 1745234502,
      "rank_change": "new"
    },
    {
      "hot_rank": 44,
      "book_id": "7613404165309484057",
      "book_name": "马甲：杀神千金，伪装柔弱小白花",
      "author": "鹿无言",
      "tags": [
        "女频悬疑",
        "悬疑",
        "悬疑恋爱",
        "推理",
        "打脸",
        "扮猪吃虎"
      ],
      "abstract": "（评分刚开，后面会涨）\n【扮猪吃虎，马甲大佬，女频，豪门，虐渣，打脸，团宠】\n六岁丢失的姜家千金被从外国贫民窟找回。\n成了家里捧在手心的“村姑”女儿\n \n顶着空有美貌的草包壳子，姜璃蹲在高中校园里装乖\n在家人面前扮演柔弱无骨的小白花。\n \n可谁能想到，一个连学都没上过的蠢货。\n入学第一天，被群嘲时，国际知名教授“离月”身份暴露\n校长：“我才求你来当教师？你却在我眼皮子底下扮猪吃虎？！”\n\n\n暗网国际榜上有名的杀手见了她，更是吓得掉头就跑。\n\n她是个屁的普通高中少女？！\n\n这明明就是国际第一，王牌杀手\n代号: 九幽\n是从尸山血海和枪林弹雨中爬出来的王者，仅凭一个名号，便能让无数商业政客、国际大佬们闻风丧胆\n\n 有人发现，她深夜出入地下拳场，一招制敌；\n有人撞见，她与国际财团掌舵人对弈，谈笑风生；\n更有人查到，她的身份，似乎与那位消失已久的顶级杀手息息相关……\n \n姜璃笑容甜美，漫不经心道：“什么杀手？我只是个普通高中生啦。”\n\n众人：？？？你管这叫普通？！\n\n当层层马甲被无情掀开，全球各界大佬排着队喊她“老大”，昔日嘲讽她的人目瞪",
      "status": "Ongoing",
      "thumb_url": "https://p3-novel-sign.byteimg.com/novel-pic/ce1efa1121bf86ff81647d0da88b690f~tplv-resize:225:300.image?lk3s=191c1ecc&x-expires=1779009346&x-signature=WeAzQVzqCYAzDx4B7vbGy%2F4xybA%3D",
      "last_chapter_time": "1778900432",
      "first_chapter_time": 1772633912,
      "rank_change": "new"
    },
    {
      "hot_rank": 47,
      "book_id": "7615965473821183038",
      "book_name": "盗墓：观影后，全员吃醋争红了眼",
      "author": "灵芝赋",
      "tags": [
        "悬疑脑洞",
        "悬疑",
        "悬疑恋爱",
        "灵异",
        "异世穿越",
        "系统",
        "穿书",
        "盗墓",
        "规则怪谈"
      ],
      "abstract": "【观影+系统+微虐+私设 OOC】\n\n无邪他们被强行拉入一个奇异的空间，以观影的形式，被迫观看另一个人的人生。\n\n她叫朝如愿，以不同的身份一次次撞入他们的生命中，原本他们不知道是她扮演的她们。\n\n她曾被吴家二叔和三叔折磨，被一枪毙命；曾在解雨辰的地下室里被灌滚烫盐水、脚筋割断、活活痛死。\n\n这场轮回里，她是他们擦肩不识的故人，是他们无法守护的爱人。\n\n黑瞎子一改平日的散漫，满心只是没有救下爱人的懊悔，和谁靠近便红眼相向的醋意；\n\n无邪恨透家族当年对她的折磨，红着眼眶一遍遍呢喃，要回去赎罪；\n\n本无牵挂、清冷如尘的张启灵，看着画面里死在他怀里的爱人，指尖发颤；\n\n素来礼仪涵养得体的解雨辰，见自己的爱人竟然是曾经被他血溅地下室的蝼蚁，挥刃刺向胸口，只为一同感受她当年的苦楚；\n\n张海客：归婉，铃兰花开了，你还会回来吗……\n\n刘丧、汪璨……\n\n张海盐、张海虾……\n\n他们一群人从陌生淡然，到心生怜悯，再到疯狂心动、悔恨交加……\n\n最后，看到他们亲密的场景，醋意横生，睁红了眼，只想将那个遍体鳞伤的小姑娘放到自己怀里抱着、哄着。\n\n这一次，当她再次踏入这个世界——换他们倾尽所有，予她一世安稳。",
      "status": "Ongoing",
      "thumb_url": "https://p3-novel-sign.byteimg.com/novel-pic/p2o03cc71fe91b1cc2649c928d3fc4b3bfb~tplv-resize:225:300.image?lk3s=191c1ecc&x-expires=1779009347&x-signature=dzZv83DLwbzrDlcfESVyMTaSmcU%3D",
      "last_chapter_time": "1778860157",
      "first_chapter_time": 1773243723,
      "rank_change": "new"
    },
    {
      "hot_rank": 48,
      "book_id": "7628665470404545598",
      "book_name": "穿成诡异贵族学院F5恶毒前女友",
      "author": "叶耶耶耶",
      "tags": [
        "女频悬疑",
        "悬疑恋爱",
        "悬疑",
        "灵异"
      ],
      "abstract": "【bg+万人迷+女嬷+1vn雄竞修罗场+多男主+系统+弹幕+诡异灵异】\n美而不自知娇软笨蛋狐狸美人x各类阴湿疯批变态男鬼\n盈枝，刚化成人形的狐狸，绑定笨蛋美人系统。\n却阴差阳错被拉去古早狗血贵族学院文中扮演恶毒女配。\n只需要在F5之间暧昧流连，勾搭完这个勾搭那个，就可以美美等着时机退场。\n可从有人坠楼摔死在盈枝面前时，一切都变了。\n……为什么会有鬼出现！\n盈枝：QAQ救救我\n——\n盈枝发现了两个问题。\n第一，她的系统失联了。\n第二，她发现这个世界的女主消失了。\n盈枝害怕被发现外来者身份，只能继续笨拙地走剧本，却没发现男主们看向她的目光愈发深沉。\n恢复视力后，盈枝误入F5的休息室。\n她惊恐地发现墙上贴满了自己的照片，随处可见自己丢失的生活物品。\n以及——\nF5们的真正面目。\n咔哒一声，门锁落下。\n黑影们贴了上来。\n“宝宝，你发现了啊。”",
      "status": "Ongoing",
      "thumb_url": "https://p3-novel-sign.byteimg.com/novel-pic/p2odd5ce5f0309e760b129c5e9b0b52c26a~tplv-resize:225:300.image?lk3s=191c1ecc&x-expires=1779009348&x-signature=R0JsBHdslidGlJ02wPV%2B5Ukego0%3D",
      "last_chapter_time": "1778852219",
      "first_chapter_time": 1776212886,
      "rank_change": "new"
    },
    {
      "hot_rank": 49,
      "book_id": "7623734399850253337",
      "book_name": "合约夫人是刑侦顾问",
      "author": "悲伤虾条的快乐一天",
      "tags": [
        "女频悬疑",
        "悬疑",
        "悬疑恋爱",
        "推理",
        "破案"
      ],
      "abstract": "她是他见过最完美的妻子。\n温柔、安静、听话。会在应酬回来时递上醒酒汤，会在家族聚会上得体微笑，从不过问他的行踪。\n陆沉舟觉得自己这笔投资太值了——三百万一年，买来一个毫无存在感的“工具人老婆”，应付催婚，省心省力。\n他甚至记不清她的脸。只知道她叫沈黎，每天在家种花、看书、等他回来。\n直到那天，刑警找上门。\n他的“花瓶妻子”正在阳台浇花。然后，她当着陆沉舟的面接过加密电话，声音骤然变了——\n冷静、锋利、不容置疑。\n三分钟，她推翻了专案组七十二小时的研判。五分钟，她画出凶手的行为画像。十分钟，嫌疑人范围从三千人缩小到三人。\n陆沉舟站在旁边，手里的咖啡凉了都没察觉。\n后来他才知道——\n他引以为傲的商业谈判技巧，在她眼里全是“情绪破绽”。\n他以为自己在“养”她，实际上整个市局都在排队叫她“沈顾问”。\n而当年被她亲手送进监狱的连环杀人犯“雕刻师”，刚刚出狱。\n那个疯子放话出来：\n“第一个，就杀她最爱的人。”\n陆沉舟看着自己脖子上被悄悄贴上的定位器，陷入了沉思——\n所以……她到底爱不爱我？\n在线等，挺急的。\n---\n#先婚后爱 #双重身份 #马甲文 #刑侦甜",
      "status": "Completed",
      "thumb_url": "https://p9-novel-sign.byteimg.com/novel-pic/p2o1420222e047d5695dd14f55889f92f44~tplv-resize:225:300.image?lk3s=191c1ecc&x-expires=1779009349&x-signature=%2FU7iDhsYIJTeO1yP%2BX%2Fhhn6zHgs%3D",
      "last_chapter_time": "1778041220",
      "first_chapter_time": 1775039260,
      "rank_change": "new"
    },
    {
      "hot_rank": 50,
      "book_id": "7609536085252639769",
      "book_name": "东北出马仙：这个弟马太败家",
      "author": "是雅雅哦",
      "tags": [
        "女频悬疑",
        "悬疑",
        "灵异",
        "搞笑轻松",
        "悬疑恋爱",
        "风水秘术"
      ],
      "abstract": "【搞笑】【悬疑灵异】【诙谐】【不滥情】【不圣母】\n\n985毕业的李平凡只想当个普通社畜，却被奶奶硬塞了个出马仙堂口，附带一群奇葩仙家：九百年道行的碎嘴子黄嘟嘟（一天不叭叭就难受）、逃荒出身的抠门清风宋叔（香火钱少一分都不行）、高冷狐仙胡秀娘（开口就是王炸）、吃货灰万红（徒子徒孙遍布全国就为偷坚果）……\n\n本想低调混日子，结果抖音直播意外爆火，一边被网友骂“封建迷信”，一边被仙家们吵得脑仁疼。更离谱的是，还有MCN老板想签她当“灵异主播”，送的“护身符”里藏着摄魂咒——这是要跟她斗法？\n\n李平凡看着供桌上那排木牌，深吸一口气：\n\n“各位，有人欺负到家门口了，怎么说？”\n\n黄嘟嘟第一个蹦起来：“骂他！我嘴快！”\n\n宋叔慢悠悠开口：“骂人可以，香火钱得先算清楚……”\n\n#985毕业回乡当神婆# #我家仙家没一个正常的# #恐怖灵异?不，是搞笑日常#",
      "status": "Ongoing",
      "thumb_url": "https://p9-novel-sign.byteimg.com/novel-pic/654766cac2ec937c2f573f85998aac07~tplv-resize:225:300.image?lk3s=191c1ecc&x-expires=1779009350&x-signature=NuZ6c%2BMOkV6rQRjSXXgBGFnbJQE%3D",
      "last_chapter_time": "1778861122",
      "first_chapter_time": 1771756791,
      "rank_change": "new"
    },
    {
      "hot_rank": 52,
      "book_id": "6963904289978715149",
      "book_name": "妖夫在上",
      "author": "Unknown",
      "tags": [
        "女频悬疑",
        "悬疑恋爱",
        "灵异",
        "1v1"
      ],
      "abstract": "我身上有块胎记，为了好看，我用纹身去遮盖它。可谁知，我找的纹身店不靠谱，竟给我纹了一只妖。从此以后，我的日子再不太平。",
      "status": "Completed",
      "thumb_url": "https://p3-novel-sign.byteimg.com/novel-images/5a982ecbed960d1a7d9e2c6316c9a9a7~tplv-resize:225:300.image?lk3s=191c1ecc&x-expires=1779009352&x-signature=j5cwzVpU77CtTHu67D%2Bq5ToUZ%2B0%3D",
      "last_chapter_time": "1715223455",
      "first_chapter_time": 1621426903,
      "rank_change": "new"
    },
    {
      "hot_rank": 54,
      "book_id": "7621795736891444286",
      "book_name": "穿越八零，我能闻到凶手的味道",
      "author": "兔子很爱吃包子",
      "tags": [
        "女频悬疑",
        "悬疑",
        "穿越",
        "推理",
        "破案",
        "悬疑恋爱"
      ],
      "abstract": "东城公安局来了个末世穿越而来的女公安。\n　　据说她的工作是从小叔那一哭二闹三上吊抢来的。\n　　据说上班第一天就遇到了杀人案。\n　　所有人都在等着她被吓破胆，乖乖把工作还回去时，她案子破了一个又一个，成为赫赫有名的女刑侦。\n　　也揭开了她父亲被杀的真相...\n　　重男轻女的爷奶居然是假的，他们要的就是她父亲一辈子烂在泥潭。\n　　母亲改嫁早死，也是别人的阴谋...\n　　吴忧冷笑一声，全部打出门，人性的贪婪她在末世早就见识过，绝对不会被糖衣炮弹给腐蚀\n　　从前的我，你敲骨吸髓，现在的我，你高攀不起！",
      "status": "Ongoing",
      "thumb_url": "https://p6-novel-sign.byteimg.com/novel-pic/p2o90ef473b0f3033cf3a3076ba0f5b0b4b~tplv-resize:225:300.image?lk3s=191c1ecc&x-expires=1779009353&x-signature=4Q%2FVOfkRx3HBk3uh2%2FMPRMuPcr0%3D",
      "last_chapter_time": "1778904090",
      "first_chapter_time": 1774587776,
      "rank_change": "new"
    },
    {
      "hot_rank": 55,
      "book_id": "7606984537834277950",
      "book_name": "景队，你真信她能听见死人说话？",
      "author": "青青园子",
      "tags": [
        "女频悬疑",
        "悬疑",
        "推理",
        "破案",
        "群像",
        "悬疑恋爱"
      ],
      "abstract": "【评分刚出，后期会涨，放心阅读】\n高富帅无神论者刑警队长VS隐形千金落魄通灵入殓师\n悬疑推理+日常互怼+现代言情+群像\n“我不是自杀，帮我......”\n“我就埋在你的脚下......”\n姜宁从小就能听到一些奇怪的声音，为此，周围人都给她贴上“神经病”的标签。\n直到入职殡仪馆，她再次真切地感知亡者低语时，决定报警寻求帮助。\n......\n而他，就是她生命里的一道光，从此为她正名......",
      "status": "Ongoing",
      "thumb_url": "https://p9-novel-sign.byteimg.com/novel-pic/p2o1a76db23acccd00a21bb8d8ab364a20e~tplv-resize:225:300.image?lk3s=191c1ecc&x-expires=1779009354&x-signature=tqpCcpmbe6cv%2FnVmE0fx8Drly08%3D",
      "last_chapter_time": "1778839257",
      "first_chapter_time": 1771141320,
      "rank_change": "new"
    },
    {
      "hot_rank": 57,
      "book_id": "7626141425612098622",
      "book_name": "让让，挡我杀人了",
      "author": "圆头圆脑圆肚皮的橘子",
      "tags": [
        "女频悬疑",
        "悬疑",
        "女强",
        "灵异",
        "无CP",
        "悬疑恋爱",
        "攻略反派"
      ],
      "abstract": "【没有恐怖标签，因为我觉得写的不恐怖，但读者说吓人，让我预警下。】\n\n【第一，女主绝对善良。第二，不要相信任何人的话。】\n池金莲的房子里藏着娘的腐尸，雪地里倒着未婚夫的僵尸，山洞里埋藏着父亲的朽尸，那都是她一个人的秘密。\n　　\n　　她的世界就是个巨大的停尸场。\n　　\n　　她喜欢以火救火，以水救水。\n　　\n　　旁人指责她，说她这是益之而厉。\n　　\n　　她想了想，在火里面撒了毒药，在水里面放了屎。\n　　\n　　对于这个时代而言，她不亚于毁灭世界的毒瘤。\n　　\n　　但身处这个时代，即使无比错误，也无限正确。",
      "status": "Ongoing",
      "thumb_url": "https://p3-novel-sign.byteimg.com/novel-pic/p2oa3d7e228d550438c5964e5bb5284dd1b~tplv-resize:225:300.image?lk3s=191c1ecc&x-expires=1779009356&x-signature=N0lyP4hyONUYjskgqoyY9Ut6rQw%3D",
      "last_chapter_time": "1778882329",
      "first_chapter_time": 1775599620,
      "rank_change": "new"
    },
    {
      "hot_rank": 58,
      "book_id": "7501990366153804825",
      "book_name": "盗墓：从1900年开始不死",
      "author": "七日宴安",
      "tags": [
        "悬疑脑洞",
        "悬疑",
        "悬疑恋爱",
        "盗墓",
        "魂穿",
        "无CP",
        "风水秘术"
      ],
      "abstract": "（评分刚出，人还很少，后面应该会涨）\n[男主+无系统+无cp+全员单箭头+剧情向+慢节奏+主角不知道剧情]\n你好，我是一个莫得感情的杀手，这是我穿越后的故事。\n前世，温祸被嫉妒他业绩的杀手同事所害，失足坠落山崖而亡。\n这一世，在盗笔世界借尸还魂的他发现自己成了一具没有感觉的尸体，还拥有了远超常人的力量。\n哈哈哈哈，那岂不是无敌了？\n虽然人被杀就会死，可他本来就是死的，谁也杀不了他。\n碰到奇怪的变异生物？杀！\n下墓偶遇缝合血尸？也杀！\n不要质疑一个职业杀手的专业能力和职业道德啊喂！\n（女频，不是快节奏爽文，作者略有考据，尽量贴合原作风格，内容覆盖1900年到2018年之间所有盗笔剧情，三石没写完的我就瞎编，有部分原创内容）\n（划重点：慢节奏大长篇！！！）",
      "status": "Ongoing",
      "thumb_url": "https://p6-novel-sign.byteimg.com/novel-pic/p2o0d0a1bfed98b6e67dec7a2f2100ca9f2~tplv-resize:225:300.image?lk3s=191c1ecc&x-expires=1779009357&x-signature=J%2FZ900uYNtljo3j9D7G1beS%2B5UI%3D",
      "last_chapter_time": "1778855430",
      "first_chapter_time": 1746693433,
      "rank_change": "new"
    },
    {
      "hot_rank": 60,
      "book_id": "7617101541752720408",
      "book_name": "盗墓：夭寿哦！竟穿成了小哥他妈",
      "author": "穷开心",
      "tags": [
        "悬疑脑洞",
        "悬疑",
        "悬疑恋爱",
        "灵异",
        "异世穿越",
        "系统",
        "穿书",
        "盗墓",
        "无敌",
        "穿越",
        "风水秘术"
      ],
      "abstract": "避雷：白玲珑没有任何cp与暧昧，只有老妈强势护崽。\n资深盗墓迷白玲珑一觉醒来，发现自己穿成了小哥那被冰封的亲妈—白玛！\n系统给她重塑了一具十八岁巅峰少女的绝美肉身，还附赠了【始祖级纯正血脉】和【满级护崽系统】。\n“叮！检测到宿主儿子正被追杀，准备放血自救！”\n深山黑市里，小哥正欲熟练地划破手掌。\n下一秒，一个磕着瓜子、看着像邻家小妹的绝色少女从天而降。\n她一脚踹碎千年变异尸蟞，空手夺下黑金古刀，反手就是一个暴栗敲在小哥后脑勺上：\n“身体发肤受之父母！谁准你动不动就放血的？退后，看妈怎么撕了它们！”\n全场死寂。\n躲在桌底的胖子惊掉下巴：“女侠，您哪条道上的？”\n少女叉着腰，理直气壮：“我是他妈！”\n从此，九门少了一个任人摆布的放血机器，多了一个被18岁绝世凶悍“老妈”全方位无死角护崽。\n别人下墓是九死一生，白玲珑下墓是“满级大佬带崽春游”。\n吴三省想设局？老娘直接把局砸了！\n汪家想搞事？老娘物理超度你们全族！\n小哥看着那个挡在自己身前徒手撕血尸的少女背影，常年冰冷的眼底罕见地闪过一丝茫然与依赖：\n“她…好像真的是我妈？”\n胖、邪抱紧大腿瑟瑟发抖：“妖寿啦！小哥不仅有妈，这妈还是个无敌的女战神！”",
      "status": "Ongoing",
      "thumb_url": "https://p9-novel-sign.byteimg.com/novel-pic/p2odc7ea6c9eda4dc01469409b9197ef8a4~tplv-resize:225:300.image?lk3s=191c1ecc&x-expires=1779009358&x-signature=aEGubKY7sKnddrBfDDd456S%2FRUg%3D",
      "last_chapter_time": "1778842825",
      "first_chapter_time": 1773497388,
      "rank_change": "new"
    },
    {
      "hot_rank": 61,
      "book_id": "7631138624515345470",
      "book_name": "盗墓：穿成小哥的双胞胎妹妹",
      "author": "穷开心",
      "tags": [
        "悬疑脑洞",
        "悬疑",
        "悬疑恋爱",
        "盗墓",
        "穿书",
        "风水秘术"
      ],
      "abstract": "【弹幕、马甲、听心声、兄妹拉扯、强强联手、妹控】\n白影穿书了，成了康巴洛部族养了18年的“祭品”，也是那位神明般强大的“张起灵”从未谋面的双胞胎妹妹。\n康巴洛秘闻，同源双生血是开启昆仑虚终极之地的唯一钥匙。\n为了摆脱被放干血的宿命，白影带着半卷帛书连夜杀出雪山，伪装成柔弱向导混进了吴三省、阿宁的下地队伍。\n她的计划很完美：暗中观察哥哥，找机会相认，然后抱大腿。\n然而她不知道的是，由于血脉反常羁绊—她那个冷酷无情的哑巴老哥，竟然能听见她的心声！\n白影根本就不知道，她一开始就暴露了。\n导致她在小哥面前卖力的演戏而不自知。\n张起灵也不拆穿，就这样静静的看着她演，刚好可以从她的心声上验证一些事情。\n白影表面瑟瑟发抖躲在角落，内心疯狂输出：\n【就这？放这么点麒麟血还不够我画半个符的。看这血尸跪的姿势，明明是在拜本小姐身上纯正的阎王血脉好吧！】\n后来……\n吴邪和胖子看着那个一路大杀四方、能单挑禁婆的“柔弱向导”，陷入了沉思。\n胖子：“小哥，你老实交代，这姑奶奶到底是谁？你怎么处处护着她？难道是你的老相好？”\n张起灵破天荒地勾了勾唇角：“我妹，亲的。”\n？？？\n说好的张家最后一个麒麟呢！怎么还带买一送一的？！",
      "status": "Ongoing",
      "thumb_url": "https://p9-novel-sign.byteimg.com/novel-pic/p2ob81a2d52c7dff8d64590a7818da58655~tplv-resize:225:300.image?lk3s=191c1ecc&x-expires=1779009359&x-signature=RWvEKzdsEr9kBdceJU5yP5BSH68%3D",
      "last_chapter_time": "1778842822",
      "first_chapter_time": 1776764876,
      "rank_change": "new"
    },
    {
      "hot_rank": 62,
      "book_id": "7592855306699295806",
      "book_name": "盗笔：当我成为穿越中转站",
      "author": "梦想穷成花三郎",
      "tags": [
        "悬疑脑洞",
        "悬疑",
        "悬疑恋爱",
        "灵异",
        "穿越"
      ],
      "abstract": "【无cp+搞笑+ooc警告+全文无虐点无脑子＋后期团宠前，前期主受慎入，非特别难以理解，常人思维】\n我叫陆凉，有点小钱，有点小颜，人生的格言就是混吃等死，所以我是啃老族的其中一员。\n父母在陆凉三岁的时候给他测了一次命，算命的说，他这人生有一次大劫，也是一次造化，日后必定大富大贵。\n他们一高兴舍弃了抓阄这种繁文缛节，从小到大给陆凉制定的计划就是清北。\n然而陆凉也不负众望的上了社会大学，俗称家里蹲大学。\n在父母离世之后，他守着城南的别墅本以为人生就这样了，银行里存着几十亿每日吃着利息就可以过活，感觉人生毫无波澜手拿把掐~\n然而事情的转折点就在20岁那年…\n他的家漏了！光洁的天花板上突然掉下来了五个人。\n奇幻的冒险从推开门的那一刻开始。\n他竟然成了时空的中转站！\n黑与白的界限模糊不清，而陆凉也成为了那可以随意进入墓道的神秘人。\n瓶邪黑花胖：谁家好人在墓室里刷牙！！！\n陆凉：我已经不奢求你们穿越给我来给我提两袋礼品，但求你们别在我上大号的时候进来行不行？真的很尴尬唉！\n谁家好人在人最脆弱的时候直接从天花板上掉下来啊！！\n五人：你以为我们想吗？被粽子追着追着就从天花板上掉下来看你上大号…",
      "status": "Ongoing",
      "thumb_url": "https://p3-novel-sign.byteimg.com/novel-pic/f84dc5af10257dccb81a76b0a2da5a20~tplv-resize:225:300.image?lk3s=191c1ecc&x-expires=1779009361&x-signature=WzugTh%2Bs22flDnCcVO0ho8jd4PE%3D",
      "last_chapter_time": "1778828063",
      "first_chapter_time": 1767853064,
      "rank_change": "new"
    },
    {
      "hot_rank": 64,
      "book_id": "7556183371848617022",
      "book_name": "僵尸：我竟成了反派？",
      "author": "一根猪",
      "tags": [
        "女频悬疑",
        "悬疑",
        "穿越",
        "灵异",
        "悬疑恋爱",
        "风水秘术"
      ],
      "abstract": "岳绮落胎穿成了岳家的假千金，六岁时，真千金岳绮罗回归，在看到真千金的那张脸后，岳绮落直接带着私房钱麻溜的滚了，只是在走之前，真千金给了她一本书，名叫《茅山剪纸术》。",
      "status": "Ongoing",
      "thumb_url": "https://p9-novel-sign.byteimg.com/novel-pic/p2o833dfe75374e7d0733a8eb0b78ec6a72~tplv-resize:225:300.image?lk3s=191c1ecc&x-expires=1779009362&x-signature=yi%2Fnh8bI%2BKlgdoFzebDOj8z1KZI%3D",
      "last_chapter_time": "1778904729",
      "first_chapter_time": 1759709472,
      "rank_change": "new"
    },
    {
      "hot_rank": 69,
      "book_id": "7619014289818389529",
      "book_name": "真千金听物破案，成重案组团宠",
      "author": "大海小棠",
      "tags": [
        "女频悬疑",
        "悬疑",
        "推理",
        "无CP",
        "破案",
        "悬疑恋爱"
      ],
      "abstract": "【与万物对话+神探+团宠女主无cp无男主无竞雄】\n　　青栀是首富沈家流落在外二十三年的真千金。\n       偶然一次靠近凶案现场，她发现自己能听见万物的声音。\n　　石板路：“天啊！这是第八个受害者了，凶手好残暴！”\n　　青砖墙：“凶手顺着下水道跑了！”\n　　花瓶：“我身上留有凶手的指纹。”\n　　沙发：“快把我掀开，我底下有凶手的犯案证据。”\n　　……\n　　她甚至还能和它们对话。\n　　进入重案组后，青栀凭着这个异能屡破大案，成了警界最耀眼的明星。",
      "status": "Ongoing",
      "thumb_url": "https://p6-novel-sign.byteimg.com/novel-pic/p2oc1350087b276204798e9479b19c425f4~tplv-resize:225:300.image?lk3s=191c1ecc&x-expires=1779009363&x-signature=OT0tqYhsJtoDZvHyRJG9fS8mhRY%3D",
      "last_chapter_time": "1778169553",
      "first_chapter_time": 1773940100,
      "rank_change": "new"
    },
    {
      "hot_rank": 70,
      "book_id": "7618080827649297470",
      "book_name": "无限：拒绝和boss贴贴",
      "author": "山呼万万岁",
      "tags": [
        "悬疑脑洞",
        "悬疑",
        "悬疑恋爱",
        "惊悚游戏"
      ],
      "abstract": "【不谙世事的正义甜妹 X 各种恋爱脑boss】\n【无限流＋阴间女嬤向＋切片＋男全洁＋无脑爽＋dt/st混合＋少量弹幕＋非女强＋身娇体软易推倒＋全男暧昧粗箭头＋（后面想到再加）】\n\n时织织因为一场怪病被关在家里整整十九年，好不容易进入了【万界】游戏，以为终于能自由自在地看看外面的世界了，结果刚进副本就发现，这游戏的打开方式好像不太对。\n\n别人进副本：打怪、升级、抢资源\n她进副本：被觊觎、被跟踪、被贴贴\n\n别人通关靠强大武力值和聪明的大脑\n她通关靠……好像什么也没靠，boss自己就自投罗网了\n\n起初，时织织以为是自己的体质在拖后腿，被人碰就会浑身发软，散发出奇异的香味，这不是行走的靶子是什么。\n后来，她慢慢意识到不对劲，怎么每个副本里的反派、boss、甚至NPC，看她的眼神都越来越不对？\n\n后来，作为榜单常年第一的时织织被人采访：所以大神，100%的通关率是怎么达成的？\n\n她茫然地眨了眨眼：“不知道啊……他们好像不等我出手，自己就先打起来了。”\n\n直播间常驻弹幕已经彻底疯狂：【让她把所有副本的boss都祸害一遍！】",
      "status": "Ongoing",
      "thumb_url": "https://p6-novel-sign.byteimg.com/novel-pic/p2o090e4aed3e600b1f7fd71379f98b7a89~tplv-resize:225:300.image?lk3s=191c1ecc&x-expires=1779009364&x-signature=8OabUkYAHPVRWvpOlDqVUJi9gKY%3D",
      "last_chapter_time": "1778838146",
      "first_chapter_time": 1773741637,
      "rank_change": "new"
    },
    {
      "hot_rank": 74,
      "book_id": "7630284013327879193",
      "book_name": "我被男友卖到缅北后",
      "author": "夏雪冬冰",
      "tags": [
        "女频悬疑",
        "悬疑",
        "悬疑恋爱"
      ],
      "abstract": "男友说带我去泰国旅游，机票酒店全包。我信了，还发了朋友圈炫耀。\n直到他被武装人员拦住，跪在地上用流利的缅语和他们讨价还价——八万五，成交。我才明白，我被自己最信任的人卖了。\n缅北诈骗园区，编号M-0237。电击、烙铁、水牢、小黑屋、抽血、断指、烙印……每一天都在地狱里挣扎......",
      "status": "Ongoing",
      "thumb_url": "https://p9-novel-sign.byteimg.com/novel-pic/p2o6b18c51257956d02179f57c63e79766e~tplv-resize:225:300.image?lk3s=191c1ecc&x-expires=1779009365&x-signature=rqvGb3AwEdjEHkOII3u08QIKNuA%3D",
      "last_chapter_time": "1778904498",
      "first_chapter_time": 1776564995,
      "rank_change": "new"
    },
    {
      "hot_rank": 76,
      "book_id": "7598990136826661913",
      "book_name": "碰倒香炉后，被千年鬼君缠上了！",
      "author": "圆未满",
      "tags": [
        "女频悬疑",
        "悬疑",
        "悬疑恋爱",
        "灵异",
        "捉鬼"
      ],
      "abstract": "半夜第三次被鬼压床，马雪妹直接掀了被子。\n“装，继续装！你也就这点本事！”\n——身为马家最后一代“编外”庙祝，她没想到自家库房那个积灰的破香炉里，真能睡出个活祖宗。\n谢垣，香炉里苏醒的千年鬼君，被吵醒后只有一个朴素的愿望：找乐子。\n而眼前这个敢跟他抢被子、还嫌他手凉的小姑娘……看起来就很有趣。\n“帮我找回一根骨头，”他懒洋洋地缠上她的头发，“找到了，我就走。”\n马雪妹：“找不到呢？”\n雾气聚成一张俊美却欠揍的脸，凑近她耳畔：“那就……拿你抵债。”\n于是，马雪妹的日常变成了：\n白天，她翻遍城市角落，寻找一根千年指骨。\n晚上，她要跟某个得寸进尺的鬼君斗智斗勇，保卫自己的床铺和尊严。\n“谢垣！你的手能不能别乱放？！”\n“冷，借点阳气。”\n“这是骚扰！”\n“哦？那你去报警啊。”鬼君笑得眉眼弯弯，“看他们信你，还是信我？”\n直到危险降临，谢垣将她护在身后，素来戏谑的声音冷如寒冰：\n“动她？问过本君了吗？”",
      "status": "Ongoing",
      "thumb_url": "https://p6-novel-sign.byteimg.com/novel-pic/212cde6a7088e18573953ec118bc549c~tplv-resize:225:300.image?lk3s=191c1ecc&x-expires=1779009366&x-signature=UZQv1uGqXS5vg31iYrkozgptfyU%3D",
      "last_chapter_time": "1778862473",
      "first_chapter_time": 1769301047,
      "rank_change": "new"
    },
    {
      "hot_rank": 81,
      "book_id": "7460100700882619416",
      "book_name": "通灵神探：她能共享凶犯视角",
      "author": "安哥一米八",
      "tags": [
        "女频悬疑",
        "悬疑恋爱",
        "悬疑",
        "推理",
        "直播",
        "无CP",
        "破案"
      ],
      "abstract": "【悬疑+破案+刑侦+无CP+讲鬼故事的女主播她原来是破案奇才？】\n“我又看见命案现场了！”从小能梦到命案现场的申媛因为怪力乱神丢了警察的工作，看遍了心理医生都说她正常的她选择上网讲述自己的梦境。\n当她再一次在直播间讲述新的梦境时，却遇到了上一个梦境的凶手当着直播观众的面杀人灭口。\n原来她讲的不是鬼故事，她真的能看见！\n没找到女儿尸身的失独父亲通过网络寻求她的帮助，她屡次打脸官方，成功找到被凶手抛尸的尸体并揪出真凶。\n姐姐同事的女儿失踪了，居然牵连着一起诡异的连环失踪案，只有整整齐齐摆放的失踪者的衣物，却怎么也找不到尸体。\n她们是死是活？跟着主角一起剥开迷雾，一起经历一个个离奇诡异的案件吧！\n\n通灵神探2已经上线，看完第一部的可以去看了",
      "status": "Completed",
      "thumb_url": "https://p9-novel-sign.byteimg.com/novel-pic/p2o9adee05070d81210360c2312e8dc2edd~tplv-resize:225:300.image?lk3s=191c1ecc&x-expires=1779009368&x-signature=YzyCvJoSz0zsPgRM7RmYJ%2Bn7XBI%3D",
      "last_chapter_time": "1762164091",
      "first_chapter_time": 1736940209,
      "rank_change": "new"
    },
    {
      "hot_rank": 83,
      "book_id": "7557429527052291096",
      "book_name": "综：魔杖今天也在跨次元加班",
      "author": "量子猫猫",
      "tags": [
        "女频悬疑",
        "悬疑",
        "灵异",
        "同人",
        "1v1",
        "悬疑恋爱"
      ],
      "abstract": "★分会慢慢涨★【HP+各种影视剧、动漫】【单元文】【原创女主】【1v1】【我流】【ooc】【拆cp】【拯救意难平】\n包括但不限于：\n【盗笔篇】梅丽x黑瞎子\n格林德沃养女和幸福瞎瞎~\n【暮光篇】莱西x凯厄斯\n与吸血鬼的三生三世（哈哈）\n【咒回篇】茉莉x五条悟\n猫猫狗狗的纯爱赛高！\n【漫威篇】艾尔西亚x史蒂夫.罗杰斯\nThat is America's ass~\n【夏目篇】久世葵x夏目贵志\n中二少女也会败给温柔么？\n【神夏篇】伊瑞斯x夏洛克·福尔摩斯\n世界有无数谜题，而你，是我唯一想要的答案。\n【小樱篇】樱田莉奈x本之本桃矢\n“亲亲狂魔”与遭遇女流氓的木之本君\n【斗罗篇】希娅x？？？？·？？？\n【番外篇】女儿们的观影茶话会＋各种篇幅较短的世界（又名：牛马希娅的快穿日记）\n简介：每一篇都是一个新的原创女主，性格会有相似或不同，两个世界的融合设定也不同，但金手指永远都是最爱的那根小木棍！！！",
      "status": "Ongoing",
      "thumb_url": "https://p6-novel-sign.byteimg.com/novel-pic/p2oe5bd0b5e728ee14572925087ebdbca59~tplv-resize:225:300.image?lk3s=191c1ecc&x-expires=1779009369&x-signature=7mlktyUClIyMuDqrQn6aAKyXw08%3D",
      "last_chapter_time": "1778904026",
      "first_chapter_time": 1759618824,
      "rank_change": "new"
    },
    {
      "hot_rank": 84,
      "book_id": "7627674049560185881",
      "book_name": "续写第十二年",
      "author": "CC梦回",
      "tags": [
        "女频悬疑",
        "悬疑",
        "悬疑恋爱",
        "推理",
        "打脸",
        "破案"
      ],
      "abstract": "十二年前，温以宁被分手时，只问了沈渡一句话：“你想好了？”\n沈渡说：“想好了。”\n温以宁转身离开京城，没掉一滴泪。\n十二年后，边境犯罪集团“沉渊”覆灭，核心人物“刽子手”在逃。唯一的卧底代号“哑巴”，被上级以保护性调令塞进了京城刑警队。\n报到那天，温以宁站在刑警队门口，看见沈渡从里面走出来。\n他穿着警服，肩上是队长的警衔。\n四目相对。\n沈渡手里的文件夹掉在地上。\n温以宁只扫了他一眼，擦肩而过。\n身后有人喊：“老沈，你认识新来的温队？”\n沈渡喉结滚动，半天才说：“……认识。”\n他曾为她收过尸。\n在每一个噩梦里。\n而现在她活着回来了——眼神像淬过毒的刀，看他的时候，没有恨，只有冷。",
      "status": "Completed",
      "thumb_url": "https://p3-novel-sign.byteimg.com/novel-pic/p2o8ff270b5a1c3156105d989ad2f6c66a5~tplv-resize:225:300.image?lk3s=191c1ecc&x-expires=1779009371&x-signature=CUNPFMweyarl1WXz%2FbcQnVaKVlM%3D",
      "last_chapter_time": "1778288439",
      "first_chapter_time": 1776663607,
      "rank_change": "new"
    },
    {
      "hot_rank": 85,
      "book_id": "7614862971293928473",
      "book_name": "她闻得出来",
      "author": "真相请说话",
      "tags": [
        "女频悬疑",
        "悬疑",
        "悬疑恋爱",
        "破案",
        "推理"
      ],
      "abstract": "我是林砚，一名法医，懂中医，会辨毒。\n见过最温柔的妻子，被枕边人藏进地下室。\n见过最善良的老人，被护工悄悄换掉汤药。\n见过最无辜的女孩，被霸凌逼到绝路。\n每一具尸体，都藏着没说出口的真相。\n每一个案件，都是撕开人性的一刀。\n我的手记里，没有华丽辞藻，\n只有最真实的罪恶，和最晚到来的正义。",
      "status": "Completed",
      "thumb_url": "https://p3-novel-sign.byteimg.com/novel-pic/360424f2fe7461e05c1af4d7e8111f21~tplv-resize:225:300.image?lk3s=191c1ecc&x-expires=1779009372&x-signature=gvZNTB13AhnJ%2Bb87zJcNYwyi12U%3D",
      "last_chapter_time": "1774266960",
      "first_chapter_time": 1772977964,
      "rank_change": "new"
    },
    {
      "hot_rank": 86,
      "book_id": "7599281121188138009",
      "book_name": "替嫁刑警飒翻天，捉鬼破案两不误",
      "author": "二月的火",
      "tags": [
        "女频悬疑",
        "悬疑恋爱",
        "日久生情",
        "全能",
        "神探",
        "代嫁代娶",
        "捉鬼"
      ],
      "abstract": "破案＋捉鬼＋甜甜的恋爱\n钟馗座下辩恶司弟子宁池，因误判忠魂触犯冥界铁律，被封七成道法罚入人间历劫，为了正常生活，魂魄附在从小被丢在乡下的宁家大小姐身上。\n　　一朝被宁家接回云城，只为了替继妹嫁给冷厉铁血的刑警队长沈问期。\n　　绿茶继妹骂她心思歹毒，夜半就被缠人的小鬼扰得魂不守舍，只能哭着求她出手化解；\n　　难缠婆婆刚想摆架子，被她三两下收拾了作妖的旁支亲戚后，从此见了她就笑脸相迎：“儿媳妇，你打了老公可不能打我啊！”\n　　下属慌张来报：“队长！嫂子又比我们先一步找到了凶手！”\n　　宁池拍掉符灰，看着眼前乖乖递上一等功的刑警队长老公，慢悠悠道：“识魂辨恶明是非，镇煞驱邪积功德，顺带帮你破个案渡个劫，懂？”\n　　沈问期喉结滚动，将人揽进怀里：“夫人的功德路，我陪你走到底。”",
      "status": "Ongoing",
      "thumb_url": "https://p6-novel-sign.byteimg.com/novel-pic/d0df94a6748d890b4a9df9381e3b607d~tplv-resize:225:300.image?lk3s=191c1ecc&x-expires=1779009373&x-signature=NCSkZHL2ZRltMXOrOPR0fskv9bE%3D",
      "last_chapter_time": "1778861079",
      "first_chapter_time": 1769522277,
      "rank_change": "new"
    },
    {
      "hot_rank": 88,
      "book_id": "7546121034655599641",
      "book_name": "意外之下",
      "author": "六六六儿",
      "tags": [
        "女频悬疑",
        "悬疑",
        "推理",
        "1v1",
        "悬疑恋爱"
      ],
      "abstract": "发现丈夫出轨，她寻到了第三者的住处，争执中，意外发生，年轻貌美又猖狂的第三者倒在了血泊里……\n意外杀人，她的生活陷入了无尽深渊，但，渐渐的，她发现这场意外中有着诸多的不对劲……",
      "status": "Completed",
      "thumb_url": "https://p3-novel-sign.byteimg.com/novel-pic/p2o0dd230d83edb98ef36ea4979bd30d773~tplv-resize:225:300.image?lk3s=191c1ecc&x-expires=1779009374&x-signature=omMki6F%2FXDcoFdNhfBP0mlOsV0k%3D",
      "last_chapter_time": "1770555752",
      "first_chapter_time": 1756973365,
      "rank_change": "new"
    },
    {
      "hot_rank": 89,
      "book_id": "7275953262476397622",
      "book_name": "盗墓：带着满级账号穿越盗笔",
      "author": "是笙笙吖",
      "tags": [
        "悬疑脑洞",
        "悬疑",
        "悬疑恋爱",
        "盗墓",
        "穿书",
        "无敌",
        "穿越"
      ],
      "abstract": "【原创女主+1v1+女主无敌+私设如山+ooc警告⚠️+游戏账号】\n明媚精致小太阳星星vs表面清冷内心戏极多大张哥\n\n沐星刚放暑假，准备去旅游，刚到机场就穿越到墓里，幸运的游戏账号也跟来了，还遇见了大张哥。短暂的几天异世穿越结束。\n\n穿回来的沐星也预感还会二次穿越，不仅在剩下的时间看完了盗墓笔记，还顺便把手上资产处理全部充进了游戏里面，买了各种各样的东西。\n\n穿越后沐星发现自己竟然可以看见张起灵的内心活动，确切的说应该是张起灵的内心活动被拟人化了，变成一个Q版张起灵。\n沐星正在教无邪如何坑人，张起灵在旁边坐得笔直看着像毫不在意，实际上他肩膀上的小起灵早就竖起耳朵手里拿着小本本记下来。手还时不时扶一下眼镜。\n【啊啊啊，小官宝宝怎么这么可爱，他是把无邪的眼镜拿过去了吗】沐星看着这一幕内心忍不住尖叫。\n——\n“张起灵，你要好好照顾自己。”\n“小官，你有不原谅的权利。”\n“你的善意从来都不是用来填补别人自私的缺口，做自己最坚定的偏爱，比什么都重要。”\n张起灵看着眼前这一路走来教自己如何爱自己的人，上前两步把沐星抱在怀里，头在沐星的肩上微微蹭了蹭，周身充斥着愉悦的气息，“星星，爱你。”",
      "status": "Completed",
      "thumb_url": "https://p9-novel-sign.byteimg.com/novel-pic/p2o2e196802b23fdac929f60ebded678fdc~tplv-resize:225:300.image?lk3s=191c1ecc&x-expires=1779009375&x-signature=jxctacKlottu7QLDQ9i%2BJ2yHPo8%3D",
      "last_chapter_time": "1778428894",
      "first_chapter_time": 1758038897,
      "rank_change": "new"
    },
    {
      "hot_rank": 93,
      "book_id": "7583698574571998232",
      "book_name": "盗墓：从宝可梦世界走到盗笔世界",
      "author": "木尧泗",
      "tags": [
        "女频悬疑",
        "悬疑",
        "穿越",
        "灵异",
        "同人",
        "悬疑恋爱"
      ],
      "abstract": "一个从现代穿越到宝可梦世界又突然到盗墓笔记世界，在这里有认识许多人，结交许多朋友，有欢喜，有遗憾，但这是一次充满色彩的异世旅行",
      "status": "Ongoing",
      "thumb_url": "https://p3-novel-sign.byteimg.com/novel-pic/p2o38ecf04eada87114ecbdfab5110bf88e~tplv-resize:225:300.image?lk3s=191c1ecc&x-expires=1779009376&x-signature=SUrtlWyinmUA5KT%2FcHrAREdllIY%3D",
      "last_chapter_time": "1778855481",
      "first_chapter_time": 1768881440,
      "rank_change": "new"
    }
  ]
}